random_slugs/__about__.py
random_slugs/__init__.py
random_slugs/generate.py
random_slugs/words.py
random_slugs-1.0.4.dist-info/METADATA
random_slugs-1.0.4.dist-info/WHEEL
random_slugs-1.0.4.dist-info/licenses/LICENSE.txt
random_slugs-1.0.4.dist-info/RECORD
