Metadata-Version: 2.3
Name: random-slugs
Version: 1.0.4
Summary: A Python package for generating random slugs using a customizable vocabulary of words.
Project-URL: Bug Reports, https://github.com/fkapsahili/random-slugs/issues
Project-URL: Homepage, https://github.com/fkapsahili/random-slugs
Project-URL: Source, https://github.com/fkapsahili/random-slugs/
Author-email: Fabio Kapsahili <fabio.kapsahili@protonmail.com>
Maintainer-email: Fabio Kapsahili <fabio.kapsahili@protonmail.com>
License: The MIT License (MIT)
License-File: LICENSE.txt
Keywords: development,sample,setuptools
Classifier: Intended Audience :: Developers
Classifier: Programming Language :: Python :: 3
Classifier: Programming Language :: Python :: 3 :: Only
Classifier: Programming Language :: Python :: 3.9
Classifier: Programming Language :: Python :: 3.10
Classifier: Programming Language :: Python :: 3.11
Classifier: Programming Language :: Python :: 3.12
Requires-Python: >=3.9
Provides-Extra: dev
Requires-Dist: check-manifest; extra == 'dev'
Provides-Extra: test
Requires-Dist: coverage; extra == 'test'
